datascience_project_0_github_guessnumber/__init__.py
datascience_project_0_github_guessnumber/command_line.py
datascience_project_0_github_guessnumber/guess_number.py
datascience_project_0_github_guessnumber-0.1.6.dist-info/AUTHORS.md
datascience_project_0_github_guessnumber-0.1.6.dist-info/LICENSE
datascience_project_0_github_guessnumber-0.1.6.dist-info/METADATA
datascience_project_0_github_guessnumber-0.1.6.dist-info/WHEEL
datascience_project_0_github_guessnumber-0.1.6.dist-info/entry_points.txt
datascience_project_0_github_guessnumber-0.1.6.dist-info/top_level.txt
datascience_project_0_github_guessnumber-0.1.6.dist-info/RECORD
