Metadata-Version: 2.1
Name: datascience-project-0-github-guessnumber
Version: 0.1.6
Summary: Data science project 0: A guess number game example with primitive self-testing
Home-page: https://github.com/dmitry-v-vlasov/data-science-course/tree/master/module_0/datascience_project_0_github_guessnumber
Author: Dmitry Vlasov
Author-email: dmitry.v.vlasov@gmail.com
License: MIT
Keywords: datascience,essentials,guessnumber
Platform: any
Classifier: Programming Language :: Python :: 3
Classifier: License :: OSI Approved :: MIT License
Classifier: Operating System :: OS Independent
Requires-Dist: setuptools
Requires-Dist: wheel
Requires-Dist: numpy
